odoo10_addon_report_hotel_reservation-10.0.1.0.0.99.dev9-py2.7-nspkg.pth
odoo/addons/report_hotel_reservation/README.rst
odoo/addons/report_hotel_reservation/__init__.py
odoo/addons/report_hotel_reservation/__manifest__.py
odoo/addons/report_hotel_reservation/Doc/ChangeLog.txt
odoo/addons/report_hotel_reservation/LICENSE/LICENSE
odoo/addons/report_hotel_reservation/i18n/es.po
odoo/addons/report_hotel_reservation/i18n/fr_BE.po
odoo/addons/report_hotel_reservation/i18n/sv.po
odoo/addons/report_hotel_reservation/models/__init__.py
odoo/addons/report_hotel_reservation/models/report_hotel_reservation.py
odoo/addons/report_hotel_reservation/security/ir.model.access.csv
odoo/addons/report_hotel_reservation/static/description/icon.png
odoo/addons/report_hotel_reservation/static/description/sbres.png
odoo/addons/report_hotel_reservation/static/description/serpent.png
odoo/addons/report_hotel_reservation/views/report_hotel_reservation_view.xml
odoo10_addon_report_hotel_reservation-10.0.1.0.0.99.dev9.dist-info/DESCRIPTION.rst
odoo10_addon_report_hotel_reservation-10.0.1.0.0.99.dev9.dist-info/METADATA
odoo10_addon_report_hotel_reservation-10.0.1.0.0.99.dev9.dist-info/RECORD
odoo10_addon_report_hotel_reservation-10.0.1.0.0.99.dev9.dist-info/WHEEL
odoo10_addon_report_hotel_reservation-10.0.1.0.0.99.dev9.dist-info/metadata.json
odoo10_addon_report_hotel_reservation-10.0.1.0.0.99.dev9.dist-info/namespace_packages.txt
odoo10_addon_report_hotel_reservation-10.0.1.0.0.99.dev9.dist-info/top_level.txt
